fasthare.cpython-310-darwin.so
fasthare-1.0.4.dist-info/LICENSE
fasthare-1.0.4.dist-info/METADATA
fasthare-1.0.4.dist-info/WHEEL
fasthare-1.0.4.dist-info/top_level.txt
fasthare-1.0.4.dist-info/RECORD
