Metadata-Version: 2.1
Name: fasthare
Version: 1.0.4
Summary: Reduce QUBO/Hamiltonian (exact reduction). Source code for the paper 'FastHare: Fast Hamiltonian Reduction for Large-scale Quantum Annealing, IEEE Int. Conf. on Quantum Computing and Engineering (QCE) 2022' https://arxiv.org/abs/2205.05004
Home-page: https://github.com/thang-dinh/FastHare
Author: Thang Dinh/Phuc Thai
Author-email: thangdn@gmail.com
Requires-Python: >=3.10
License-File: LICENSE
Provides-Extra: test
Requires-Dist: pytest; extra == "test"
